{
  "$schema": "https://mintlify.com/docs.json",
  "name": "Finance Agent",
  "theme": "sequoia",
  "colors": {
    "primary": "#2563EB",
    "light": "#60A5FA",
    "dark": "#1E40AF"
  },
  "navbar": {
    "primary": {
      "type": "github",
      "href": "https://github.com/kamathhrishi/finance-agent"
    }
  },
  "footer": {
    "socials": {
      "github": "https://github.com/kamathhrishi/finance-agent"
    }
  },
  "navigation": {
    "tabs": [
      {
        "tab": "Documentation",
        "groups": [
          {
            "group": "Get Started",
            "pages": [
              "introduction",
              "quickstart",
              "installation"
            ]
          },
          {
            "group": "Core Concepts",
            "pages": [
              "concepts/agent-architecture",
              "concepts/semantic-routing",
              "concepts/rag-pipeline",
              "concepts/data-sources"
            ]
          },
          {
            "group": "Features",
            "pages": [
              "features/earnings-transcripts",
              "features/sec-filings",
              "features/real-time-news",
              "features/financial-screener"
            ]
          },
          {
            "group": "Guides",
            "pages": [
              "guides/asking-questions",
              "guides/data-ingestion",
              "guides/configuration",
              "guides/authentication"
            ]
          },
          {
            "group": "Agent System",
            "pages": [
              "agent/overview",
              "agent/pipeline-stages",
              "agent/iterative-improvement",
              "agent/sec-agent"
            ]
          }
        ]
      },
      {
        "tab": "API Reference",
        "groups": [
          {
            "group": "Overview",
            "pages": [
              "api/overview",
              "api/authentication"
            ]
          },
          {
            "group": "Endpoints",
            "pages": [
              "api/chat",
              "api/companies",
              "api/financials",
              "api/transcripts",
              "api/sec-filings",
              "api/screener"
            ]
          },
          {
            "group": "Python API",
            "pages": [
              "api/python/agent",
              "api/python/rag-agent",
              "api/python/search-engine"
            ]
          }
        ]
      },
      {
        "tab": "Development",
        "groups": [
          {
            "group": "Setup",
            "pages": [
              "development/local-setup",
              "development/environment-variables",
              "development/database-setup"
            ]
          },
          {
            "group": "Architecture",
            "pages": [
              "development/project-structure",
              "development/tech-stack",
              "development/database-schema"
            ]
          },
          {
            "group": "Contributing",
            "pages": [
              "development/contributing",
              "development/testing"
            ]
          }
        ]
      }
    ]
  }
}
